pdf_suite/__init__.py
pdf_suite/cli.py
pdf_suite/compress.py
pdf_suite/docx2pdf.py
pdf_suite/merger.py
pdf_suite/pdf2img.py
pdf_suite/pdfinfo.py
pdf_suite/py.typed
pdf_suite/command_line/__init__.py
pdf_suite/command_line/command_line.py
pdf_suite/helper/__init__.py
pdf_suite/helper/file.py
pdf_suite/helper/filesize.py
pdf_suite/helper/output.py
pdf_suite/helper/percentage.py
pdf_suite-0.9.0.dist-info/LICENSE
pdf_suite-0.9.0.dist-info/METADATA
pdf_suite-0.9.0.dist-info/WHEEL
pdf_suite-0.9.0.dist-info/entry_points.txt
pdf_suite-0.9.0.dist-info/top_level.txt
pdf_suite-0.9.0.dist-info/RECORD
